LICENSE
README.md
setup.cfg
setup.py
src/Flask_Lib.egg-info/PKG-INFO
src/Flask_Lib.egg-info/SOURCES.txt
src/Flask_Lib.egg-info/dependency_links.txt
src/Flask_Lib.egg-info/requires.txt
src/Flask_Lib.egg-info/top_level.txt
src/flasklib/__init__.py
src/flasklib/dates.py
src/flasklib/errors.py
src/flasklib/jinja.py
src/flasklib/json.py
src/flasklib/responses.py
src/flasklib/startup.py
src/flasklib/mappers/__init__.py
src/flasklib/mappers/mappers.py