Metadata-Version: 1.2
Name: Flask-Lib
Version: 0.2.3
Summary: Premade Flask tools to speed up development.
Home-page: https://github.com/rrickgauer/Flask-Lib
Author: Ryan Rickgauer
Author-email: rrickgauer1@gmail.com
License: UNKNOWN
Platform: UNKNOWN
Requires-Python: >=3.8
